Metadata-Version: 2.1
Name: d3dslic3r
Version: 0.4
Summary: DED SLICER
Home-page: https://github.com/majroy/d3dslic3r
Author: M J Roy
Author-email: matthew.roy@manchester.ac.uk
License: Creative Commons Attribution-Noncommercial-Share Alike license
Keywords: 3D printing,direct energy deposition,slicer,computer aided manufacturing
Classifier: Development Status :: 3 - Alpha
Classifier: Environment :: Win32 (MS Windows)
Classifier: Topic :: Scientific/Engineering :: Visualization
Classifier: License :: OSI Approved :: GNU General Public License v3 or later (GPLv3+)
Classifier: Operating System :: Microsoft :: Windows :: Windows 10
Classifier: Programming Language :: Python :: 3.11
Classifier: Intended Audience :: End Users/Desktop
Classifier: Natural Language :: English
License-File: LICENSE
Requires-Dist: vtk>=6.0
Requires-Dist: numpy
Requires-Dist: scipy
Requires-Dist: pyyaml>=5.0
Requires-Dist: matplotlib
Requires-Dist: PyQt5>=5
Requires-Dist: h5py
Requires-Dist: scikit-learn
Requires-Dist: shapely
Requires-Dist: pyclipper
